wristband/py.typed
wristband/fastapi_auth/__init__.py
wristband/fastapi_auth/auth.py
wristband/fastapi_auth/client.py
wristband/fastapi_auth/config_resolver.py
wristband/fastapi_auth/csrf.py
wristband/fastapi_auth/exceptions.py
wristband/fastapi_auth/middleware.py
wristband/fastapi_auth/models.py
wristband/fastapi_auth/session.py
wristband/fastapi_auth/utils.py
wristband_fastapi_auth-2.0.0.dist-info/licenses/LICENSE
wristband_fastapi_auth-2.0.0.dist-info/METADATA
wristband_fastapi_auth-2.0.0.dist-info/WHEEL
wristband_fastapi_auth-2.0.0.dist-info/top_level.txt
wristband_fastapi_auth-2.0.0.dist-info/RECORD
